{"cameraMode":{"drawMode":0,"name":"Shaded","section":"Shading Mode"},"sceneLighting":false,"audioPlay":false,"sceneViewState":{"m_AlwaysRefresh":false,"showFog":true,"showSkybox":false,"showFlares":true,"showImageEffects":true,"showParticleSystems":true,"showVisualEffectGraphs":true,"m_FxEnabled":true},"in2DMode":false,"pivot":{"x":0.21305547654628755,"y":-0.007556989789009094,"z":-0.0014878250658512116},"rotation":{"x":-0.06801141053438187,"y":0.9295487999916077,"z":-0.21893230080604554,"w":-0.28876498341560366},"size":0.2958170771598816,"orthographic":false}